{
  "Name": "azurerm_cdn_endpoint",
  "swagger": "",
  "PropertyLinks": {
    "content_types_to_compress": [],
    "delivery_rule.cache_expiration_action.behavior": [],
    "delivery_rule.cache_expiration_action.duration": [],
    "delivery_rule.cache_key_query_string_action.behavior": [],
    "delivery_rule.cache_key_query_string_action.parameters": [],
    "delivery_rule.cookies_condition.match_values": [],
    "delivery_rule.cookies_condition.negate_condition": [],
    "delivery_rule.cookies_condition.operator": [],
    "delivery_rule.cookies_condition.selector": [],
    "delivery_rule.cookies_condition.transforms": [],
    "delivery_rule.device_condition.match_values": [],
    "delivery_rule.device_condition.negate_condition": [],
    "delivery_rule.device_condition.operator": [],
    "delivery_rule.http_version_condition.match_values": [],
    "delivery_rule.http_version_condition.negate_condition": [],
    "delivery_rule.http_version_condition.operator": [],
    "delivery_rule.modify_request_header_action.action": [],
    "delivery_rule.modify_request_header_action.name": [],
    "delivery_rule.modify_request_header_action.value": [],
    "delivery_rule.modify_response_header_action.action": [],
    "delivery_rule.modify_response_header_action.name": [],
    "delivery_rule.modify_response_header_action.value": [],
    "delivery_rule.name": [],
    "delivery_rule.order": [],
    "delivery_rule.post_arg_condition.match_values": [],
    "delivery_rule.post_arg_condition.negate_condition": [],
    "delivery_rule.post_arg_condition.operator": [],
    "delivery_rule.post_arg_condition.selector": [],
    "delivery_rule.post_arg_condition.transforms": [],
    "delivery_rule.query_string_condition.match_values": [],
    "delivery_rule.query_string_condition.negate_condition": [],
    "delivery_rule.query_string_condition.operator": [],
    "delivery_rule.query_string_condition.transforms": [],
    "delivery_rule.remote_address_condition.match_values": [],
    "delivery_rule.remote_address_condition.negate_condition": [],
    "delivery_rule.remote_address_condition.operator": [],
    "delivery_rule.request_body_condition.match_values": [],
    "delivery_rule.request_body_condition.negate_condition": [],
    "delivery_rule.request_body_condition.operator": [],
    "delivery_rule.request_body_condition.transforms": [],
    "delivery_rule.request_header_condition.match_values": [],
    "delivery_rule.request_header_condition.negate_condition": [],
    "delivery_rule.request_header_condition.operator": [],
    "delivery_rule.request_header_condition.selector": [],
    "delivery_rule.request_header_condition.transforms": [],
    "delivery_rule.request_method_condition.match_values": [],
    "delivery_rule.request_method_condition.negate_condition": [],
    "delivery_rule.request_method_condition.operator": [],
    "delivery_rule.request_scheme_condition.match_values": [],
    "delivery_rule.request_scheme_condition.negate_condition": [],
    "delivery_rule.request_scheme_condition.operator": [],
    "delivery_rule.request_uri_condition.match_values": [],
    "delivery_rule.request_uri_condition.negate_condition": [],
    "delivery_rule.request_uri_condition.operator": [],
    "delivery_rule.request_uri_condition.transforms": [],
    "delivery_rule.url_file_extension_condition.match_values": [],
    "delivery_rule.url_file_extension_condition.negate_condition": [],
    "delivery_rule.url_file_extension_condition.operator": [],
    "delivery_rule.url_file_extension_condition.transforms": [],
    "delivery_rule.url_file_name_condition.match_values": [],
    "delivery_rule.url_file_name_condition.negate_condition": [],
    "delivery_rule.url_file_name_condition.operator": [],
    "delivery_rule.url_file_name_condition.transforms": [],
    "delivery_rule.url_path_condition.match_values": [],
    "delivery_rule.url_path_condition.negate_condition": [],
    "delivery_rule.url_path_condition.operator": [],
    "delivery_rule.url_path_condition.transforms": [],
    "delivery_rule.url_redirect_action.fragment": [],
    "delivery_rule.url_redirect_action.hostname": [],
    "delivery_rule.url_redirect_action.path": [],
    "delivery_rule.url_redirect_action.protocol": [],
    "delivery_rule.url_redirect_action.query_string": [],
    "delivery_rule.url_redirect_action.redirect_type": [],
    "delivery_rule.url_rewrite_action.destination": [],
    "delivery_rule.url_rewrite_action.preserve_unmatched_path": [],
    "delivery_rule.url_rewrite_action.source_pattern": [],
    "geo_filter.action": [],
    "geo_filter.country_codes": [],
    "geo_filter.relative_path": [],
    "global_delivery_rule.cache_expiration_action.behavior": [],
    "global_delivery_rule.cache_expiration_action.duration": [],
    "global_delivery_rule.cache_key_query_string_action.behavior": [],
    "global_delivery_rule.cache_key_query_string_action.parameters": [],
    "global_delivery_rule.modify_request_header_action.action": [],
    "global_delivery_rule.modify_request_header_action.name": [],
    "global_delivery_rule.modify_request_header_action.value": [],
    "global_delivery_rule.modify_response_header_action.action": [],
    "global_delivery_rule.modify_response_header_action.name": [],
    "global_delivery_rule.modify_response_header_action.value": [],
    "global_delivery_rule.url_redirect_action.fragment": [],
    "global_delivery_rule.url_redirect_action.hostname": [],
    "global_delivery_rule.url_redirect_action.path": [],
    "global_delivery_rule.url_redirect_action.protocol": [],
    "global_delivery_rule.url_redirect_action.query_string": [],
    "global_delivery_rule.url_redirect_action.redirect_type": [],
    "global_delivery_rule.url_rewrite_action.destination": [],
    "global_delivery_rule.url_rewrite_action.preserve_unmatched_path": [],
    "global_delivery_rule.url_rewrite_action.source_pattern": [],
    "host_name": [],
    "id": [],
    "is_compression_enabled": [],
    "is_http_allowed": [],
    "is_https_allowed": [],
    "location": [],
    "name": [],
    "optimization_type": [],
    "origin.host_name": [],
    "origin.http_port": [],
    "origin.https_port": [],
    "origin.name": [],
    "origin_host_header": [],
    "origin_path": [],
    "probe_path": [],
    "profile_name": [],
    "querystring_caching_behaviour": [],
    "resource_group_name": [],
    "tags": [],
    "timeouts.create": [],
    "timeouts.delete": [],
    "timeouts.read": [],
    "timeouts.update": []
  }
}